neuralcore/NeuralCore.py
neuralcore/__init__.py
neuralcore-1.0.9.dist-info/METADATA
neuralcore-1.0.9.dist-info/WHEEL
neuralcore-1.0.9.dist-info/top_level.txt
neuralcore-1.0.9.dist-info/RECORD
