Metadata-Version: 2.4
Name: NeuralCore
Version: 1.0.9
Summary: A Python client for NeuralCore AI APIs
Home-page: https://neuralcore.org
Author: NeuralCore
Author-email: neuralcoreorganization@gmail.com
Classifier: Programming Language :: Python :: 3
Classifier: License :: OSI Approved :: MIT License
Classifier: Operating System :: OS Independent
Requires-Python: >=3.6
Requires-Dist: requests>=2.25.1
Dynamic: author
Dynamic: author-email
Dynamic: classifier
Dynamic: description
Dynamic: description-content-type
Dynamic: home-page
Dynamic: requires-dist
Dynamic: requires-python
Dynamic: summary
